quantlet_streaming/__init__.py
quantlet_streaming/_version.py
quantlet_streaming/dataframe.py
quantlet_streaming/iterables.py
quantlet_streaming/metadata.py
quantlet_streaming/stream.py
quantlet.streaming-1.0.0.dist-info/LICENSE
quantlet.streaming-1.0.0.dist-info/WHEEL
quantlet.streaming-1.0.0.dist-info/METADATA
quantlet.streaming-1.0.0.dist-info/RECORD
